{"nodes": [{"id": "home_emily_desktop_projects_cc_test_data_science_data_engineering_etl_forex_oanda_headers_py", "label": "headers.py", "file_type": "code", "source_file": "oanda/headers.py", "source_location": "L1"}, {"id": "oanda_headers_get_oanda_headers", "label": "get_oanda_headers()", "file_type": "code", "source_file": "oanda/headers.py", "source_location": "L2"}], "edges": [{"source": "home_emily_desktop_projects_cc_test_data_science_data_engineering_etl_forex_oanda_headers_py", "target": "oanda_headers_get_oanda_headers", "relation": "contains", "confidence": "EXTRACTED", "source_file": "oanda/headers.py", "source_location": "L2", "weight": 1.0}], "raw_calls": []}