{"nodes": [{"id": "forex_how_to_start_forex_pipeline_doc", "label": "How to Start Forex Pipeline", "file_type": "document", "source_file": "how_to_start_forex_pipeline.md", "source_location": null, "source_url": null, "captured_at": null, "author": null, "contributor": null}, {"id": "forex_how_to_start_forex_pipeline_candlestick_flow", "label": "candlestick_flow", "file_type": "code", "source_file": "how_to_start_forex_pipeline.md", "source_location": "Line 16", "source_url": null, "captured_at": null, "author": null, "contributor": null}, {"id": "forex_how_to_start_forex_pipeline_forward_fill_flow", "label": "forward_fill_flow", "file_type": "code", "source_file": "how_to_start_forex_pipeline.md", "source_location": "Line 30", "source_url": null, "captured_at": null, "author": null, "contributor": null}, {"id": "forex_how_to_start_forex_pipeline_prefect", "label": "Prefect Orchestration Framework", "file_type": "concept", "source_file": "how_to_start_forex_pipeline.md", "source_location": "Line 6", "source_url": null, "captured_at": null, "author": null, "contributor": null}, {"id": "forex_how_to_start_forex_pipeline_oanda_config", "label": "Oanda Config JSON", "file_type": "concept", "source_file": "how_to_start_forex_pipeline.md", "source_location": "Line 9", "source_url": null, "captured_at": null, "author": null, "contributor": null}, {"id": "forex_how_to_start_forex_pipeline_aws_secrets_manager", "label": "AWS Secrets Manager", "file_type": "concept", "source_file": "how_to_start_forex_pipeline.md", "source_location": "Line 10", "source_url": null, "captured_at": null, "author": null, "contributor": null}, {"id": "forex_how_to_start_forex_pipeline_influxdb", "label": "InfluxDB", "file_type": "concept", "source_file": "how_to_start_forex_pipeline.md", "source_location": "Line 10", "source_url": null, "captured_at": null, "author": null, "contributor": null}, {"id": "forex_how_to_start_forex_pipeline_check_market_open_task", "label": "check_market_open_task", "file_type": "code", "source_file": "how_to_start_forex_pipeline.md", "source_location": "Line 75", "source_url": null, "captured_at": null, "author": null, "contributor": null, "rationale": "Returns early without fetching when outside trading hours, allowing aggressive cron scheduling without wasted API calls to Oanda."}, {"id": "forex_how_to_start_forex_pipeline_cron_schedule", "label": "CronSchedule (prefect.schedules)", "file_type": "concept", "source_file": "how_to_start_forex_pipeline.md", "source_location": "Line 68", "source_url": null, "captured_at": null, "author": null, "contributor": null}, {"id": "forex_how_to_start_forex_pipeline_prefect_server", "label": "Prefect Server", "file_type": "concept", "source_file": "how_to_start_forex_pipeline.md", "source_location": "Line 39", "source_url": null, "captured_at": null, "author": null, "contributor": null}], "edges": [{"source": "forex_how_to_start_forex_pipeline_doc", "target": "forex_how_to_start_forex_pipeline_candlestick_flow", "relation": "references", "confidence": "EXTRACTED", "confidence_score": 1.0, "source_file": "how_to_start_forex_pipeline.md", "source_location": "Line 16", "weight": 1.0}, {"source": "forex_how_to_start_forex_pipeline_doc", "target": "forex_how_to_start_forex_pipeline_forward_fill_flow", "relation": "references", "confidence": "EXTRACTED", "confidence_score": 1.0, "source_file": "how_to_start_forex_pipeline.md", "source_location": "Line 30", "weight": 1.0}, {"source": "forex_how_to_start_forex_pipeline_doc", "target": "forex_how_to_start_forex_pipeline_prefect", "relation": "references", "confidence": "EXTRACTED", "confidence_score": 1.0, "source_file": "how_to_start_forex_pipeline.md", "source_location": "Line 6", "weight": 1.0}, {"source": "forex_how_to_start_forex_pipeline_candlestick_flow", "target": "forex_how_to_start_forex_pipeline_oanda_config", "relation": "references", "confidence": "EXTRACTED", "confidence_score": 1.0, "source_file": "how_to_start_forex_pipeline.md", "source_location": "Line 18", "weight": 1.0}, {"source": "forex_how_to_start_forex_pipeline_candlestick_flow", "target": "forex_how_to_start_forex_pipeline_aws_secrets_manager", "relation": "references", "confidence": "EXTRACTED", "confidence_score": 1.0, "source_file": "how_to_start_forex_pipeline.md", "source_location": "Line 10", "weight": 1.0}, {"source": "forex_how_to_start_forex_pipeline_aws_secrets_manager", "target": "forex_how_to_start_forex_pipeline_influxdb", "relation": "references", "confidence": "EXTRACTED", "confidence_score": 1.0, "source_file": "how_to_start_forex_pipeline.md", "source_location": "Line 10", "weight": 1.0}, {"source": "forex_how_to_start_forex_pipeline_candlestick_flow", "target": "forex_how_to_start_forex_pipeline_check_market_open_task", "relation": "references", "confidence": "EXTRACTED", "confidence_score": 1.0, "source_file": "how_to_start_forex_pipeline.md", "source_location": "Line 75", "weight": 1.0}, {"source": "forex_how_to_start_forex_pipeline_candlestick_flow", "target": "forex_how_to_start_forex_pipeline_cron_schedule", "relation": "references", "confidence": "EXTRACTED", "confidence_score": 1.0, "source_file": "how_to_start_forex_pipeline.md", "source_location": "Lines 68-72", "weight": 1.0}, {"source": "forex_how_to_start_forex_pipeline_candlestick_flow", "target": "forex_how_to_start_forex_pipeline_prefect", "relation": "references", "confidence": "EXTRACTED", "confidence_score": 1.0, "source_file": "how_to_start_forex_pipeline.md", "source_location": "Line 16", "weight": 1.0}, {"source": "forex_how_to_start_forex_pipeline_forward_fill_flow", "target": "forex_how_to_start_forex_pipeline_prefect", "relation": "references", "confidence": "EXTRACTED", "confidence_score": 1.0, "source_file": "how_to_start_forex_pipeline.md", "source_location": "Line 30", "weight": 1.0}, {"source": "forex_how_to_start_forex_pipeline_prefect_server", "target": "forex_how_to_start_forex_pipeline_prefect", "relation": "references", "confidence": "EXTRACTED", "confidence_score": 1.0, "source_file": "how_to_start_forex_pipeline.md", "source_location": "Line 39", "weight": 1.0}, {"source": "forex_how_to_start_forex_pipeline_cron_schedule", "target": "forex_how_to_start_forex_pipeline_prefect", "relation": "references", "confidence": "EXTRACTED", "confidence_score": 1.0, "source_file": "how_to_start_forex_pipeline.md", "source_location": "Line 68", "weight": 1.0}, {"source": "forex_how_to_start_forex_pipeline_forward_fill_flow", "target": "forex_how_to_start_forex_pipeline_candlestick_flow", "relation": "shares_data_with", "confidence": "INFERRED", "confidence_score": 0.85, "source_file": "how_to_start_forex_pipeline.md", "source_location": "Lines 26-30", "weight": 1.0}, {"source": "forex_how_to_start_forex_pipeline_candlestick_flow", "target": "forex_how_to_start_forex_pipeline_forward_fill_flow", "relation": "semantically_similar_to", "confidence": "INFERRED", "confidence_score": 0.85, "source_file": "how_to_start_forex_pipeline.md", "source_location": null, "weight": 1.0}, {"source": "forex_how_to_start_forex_pipeline_check_market_open_task", "target": "forex_how_to_start_forex_pipeline_cron_schedule", "relation": "conceptually_related_to", "confidence": "INFERRED", "confidence_score": 0.75, "source_file": "how_to_start_forex_pipeline.md", "source_location": "Line 75", "weight": 1.0}], "hyperedges": [{"id": "forex_etl_prefect_deployment", "label": "Prefect-Orchestrated Forex ETL Pipeline Deployment", "nodes": ["forex_how_to_start_forex_pipeline_candlestick_flow", "forex_how_to_start_forex_pipeline_forward_fill_flow", "forex_how_to_start_forex_pipeline_prefect_server", "forex_how_to_start_forex_pipeline_cron_schedule"], "relation": "implement", "confidence": "EXTRACTED", "confidence_score": 1.0, "source_file": "how_to_start_forex_pipeline.md"}, {"id": "forex_etl_credential_chain", "label": "Forex ETL Credential Chain", "nodes": ["forex_how_to_start_forex_pipeline_oanda_config", "forex_how_to_start_forex_pipeline_aws_secrets_manager", "forex_how_to_start_forex_pipeline_influxdb"], "relation": "participate_in", "confidence": "EXTRACTED", "confidence_score": 1.0, "source_file": "how_to_start_forex_pipeline.md"}]}